LICENSE
README.md
setup.py
monoscript/__init__.py
monoscript/__main__.py
monoscript/color_print.py
monoscript/merger.py
monoscript/parser.py
monoscript.egg-info/PKG-INFO
monoscript.egg-info/SOURCES.txt
monoscript.egg-info/dependency_links.txt
monoscript.egg-info/top_level.txt