Metadata-Version: 2.1
Name: monoscript
Version: 1.0.3
Summary: A Python tool that merges multi-file modules into a single, self-contained script.
Home-page: https://github.com/xaled/monoscript
Author: Khalid Grandi
Author-email: kh.grandi@gmail.com
License: MIT
Keywords: packaging python
Platform: UNKNOWN
Classifier: License :: OSI Approved :: MIT License
Classifier: Operating System :: OS Independent
Classifier: Programming Language :: Python
Requires-Python: >=3
License-File: LICENSE
